{
    "Dawbon" : [
    {"st_eng":"10th Street","st_myn":"၁၀ လမ်း"},
    {"st_eng":"11st Street","st_myn":"၁၁ လမ်း"},
    {"st_eng":"11th Street","st_myn":"၁၁ လမ်း"},
    {"st_eng":"12nd Street","st_myn":"၁၂ လမ်း"},
    {"st_eng":"12th Street","st_myn":"၁၂ လမ်း"},
    {"st_eng":"13rd Street","st_myn":"၁၃ လမ်း"},
    {"st_eng":"13th Street","st_myn":"၁၃ လမ်း"},
    {"st_eng":"1st Street","st_myn":"၁ လမ်း"},
    {"st_eng":"80 Ft Street","st_myn":"ပေ ၈၀ လမ်း"},
    {"st_eng":"8th Street","st_myn":"၁၈လမ်း"},
    {"st_eng":"8th Street","st_myn":"၈ လမ်း"},
    {"st_eng":"9th Street","st_myn":"၉ လမ်း"},
    {"st_eng":"Ah Lin Yaung 1st Street","st_myn":"အလင်းရောင် ၁ လမ်း"},
    {"st_eng":"Ah Lin Yaung 2nd Street","st_myn":"အလင်းရောင် ၂ လမ်း"},
    {"st_eng":"Ah Lin Yaung Street","st_myn":"အလင်းရောင်လမ်း"},
    {"st_eng":"Anawrahta Street","st_myn":"အနော်ရထာလမ်း"},
    {"st_eng":"Aung Chan Thar Street","st_myn":"အောင်ချမ်းသာလမ်း"},
    {"st_eng":"Aung Mate Swe Street","st_myn":"အောင်မိတ်ဆွေလမ်း"},
    {"st_eng":"Aung Mingalar Street","st_myn":"အောင်မင်္ဂလာလမ်း"},
    {"st_eng":"Aung Myittar Kannar Street","st_myn":"အောင်မေတ္တာကမ်းနားလမ်း"},
    {"st_eng":"Aung Myittar Middle Street","st_myn":"အောင်မေတ္တာအလယ်လမ်း"},
    {"st_eng":"Aung Myittar Street","st_myn":"အောင်မေတ္တာလမ်း"},
    {"st_eng":"Aung Myittar Upper Street","st_myn":"အောင်မေတ္တာအထက်လမ်း"},
    {"st_eng":"Aung Tagun Street","st_myn":"အောင်တံခွန်လမ်း"},
    {"st_eng":"Aung Thapyay Street","st_myn":"အောင်သပြေလမ်း"},
    {"st_eng":"Aung Tharaphu Street","st_myn":"အောင်သရဖူလမ်း"},
    {"st_eng":"Aung Thayaphu Street","st_myn":"အောင်သရဖူလမ်း"},
    {"st_eng":"Aung Theikdi Street","st_myn":"အောင်သိဒ္ဓိလမ်း"},
    {"st_eng":"Aung Thida Street","st_myn":"အောင်သီတာလမ်း"},
    {"st_eng":"Aung Thiri Street","st_myn":"အောင်သီရိလမ်း"},
    {"st_eng":"Aung Thitsar Street","st_myn":"အောင်သစ္စာလမ်း"},
    {"st_eng":"Aung Thuka Street","st_myn":"အောင်သုခလမ်း"},
    {"st_eng":"Aung Thukha Street","st_myn":"အောင်သုခလမ်း"},
    {"st_eng":"Aung Yadanar Street","st_myn":"အောင်ရတနာလမ်း"},
    {"st_eng":"Aung Zaya Street","st_myn":"အောင်ဇေယျလမ်း"},
    {"st_eng":"Aye Zay Di Street","st_myn":"အေးစေတီလမ်း"},
    {"st_eng":"Banyar Dala Street","st_myn":"ဗညားဒလလမ်း"},
    {"st_eng":"Bayint Naung 1st Street","st_myn":"ဘုရင့်နောင် ၁ လမ်း"},
    {"st_eng":"Bayint Naung 1st Street","st_myn":"ဘုရင့်နောင်(၁)လမ်း"},
    {"st_eng":"Bayint Naung 2nd Street","st_myn":"ဘုရင့်နောင် ၂ လမ်း"},
    {"st_eng":"Bayint Naung Street","st_myn":"ဘုရင့်နောင်လမ်း"},
    {"st_eng":"Bo Aung Kyaw Street","st_myn":"ဗိုလ်အောင်ကျော်လမ်း"},
    {"st_eng":"Bo La Yaung Street","st_myn":"ဗိုလ်လရောင်လမ်း"},
    {"st_eng":"Bo Min Yaung Street","st_myn":"ဗိုလ်မင်းရောင်လမ်း"},
    {"st_eng":"Bo Myat Tun 1st Street","st_myn":"ဗိုလ်မြတ်ထွန်း ၁ လမ်း"},
    {"st_eng":"Bo Myat Tun 2nd Street","st_myn":"ဗိုလ်မြတ်ထွန်း ၂ လမ်း"},
    {"st_eng":"Bo Myat Tun Street","st_myn":"ဗိုလ်မြတ်ထွန်းလမ်း"},
    {"st_eng":"Bo Soon Pat Street","st_myn":"ဗိုလ်ဆွန်ပက်လမ်း"},
    {"st_eng":"Bo Tayza Street","st_myn":"ဗိုလ်တေဇလမ်း"},
    {"st_eng":"Bogyoke 1st Street","st_myn":"ဗိုလ်ချုပ် ၁ လမ်း"},
    {"st_eng":"Bogyoke 2nd Street","st_myn":"ဗိုလ်ချုပ် ၂ လမ်း"},
    {"st_eng":"Bogyoke Aung San Street","st_myn":"ဗိုလ်ချုပ်အောင်ဆန်းလမ်း"},
    {"st_eng":"Bogyoke Street","st_myn":"ဗိုလ်ချုပ်လမ်း"},
    {"st_eng":"Dhama Yeik Thar Street","st_myn":"ဓမ္မရိပ်သာလမ်း"},
    {"st_eng":"Dhama Zedi Street","st_myn":"ဓမ္မစေတီလမ်း"},
    {"st_eng":"Dhamar Yon Street","st_myn":"ဓမ္မာရုံလမ်း"},
    {"st_eng":"Dockyard 2nd Street","st_myn":"သင်္ဘောကျင်း ၂ လမ်း"},
    {"st_eng":"Dockyard 3rd Street","st_myn":"သင်္ဘောကျင်း ၃ လမ်း"},
    {"st_eng":"Dockyard 4th Street","st_myn":"သင်္ဘောကျင်း ၄ လမ်း"},
    {"st_eng":"Dockyard 5th Street","st_myn":"သင်္ဘောကျင်း ၅ လမ်း"},
    {"st_eng":"Dockyard 6th Street","st_myn":"သင်္ဘောကျင်း ၆ လမ်း"},
    {"st_eng":"Dockyard 7th Street","st_myn":"သင်္ဘောကျင်း ၇ လမ်း"},
    {"st_eng":"Dockyard 8th Street","st_myn":"သင်္ဘောကျင်း ၈ လမ်း"},
    {"st_eng":"Dockyard 9th Street","st_myn":"သင်္ဘောကျင်း ၉ လမ်း"},
    {"st_eng":"Dockyard Street","st_myn":"သင်္ဘောကျင်းလမ်း"},
    {"st_eng":"Doe Shwe Taung Street","st_myn":"ဒို့ရွှေတောင်လမ်း"},
    {"st_eng":"Hnin Si Street","st_myn":"နှင်းဆီလမ်း"},
    {"st_eng":"Kan Tharyar Street","st_myn":"ကမ်းသာယာလမ်း"},
    {"st_eng":"Kan Yeik Thar Street","st_myn":"ကန်ရိပ်သာလမ်း"},
    {"st_eng":"Kannar Street","st_myn":"ကမ်းနားလမ်း"},
    {"st_eng":"Khay Mar Thwe Street","st_myn":"ခေမာသွယ်လမ်း"},
    {"st_eng":"Kutoe Sate Street","st_myn":"ကူးတို ့ဆိပ်လမ်း"},
    {"st_eng":"Kwet Thit 1st Street","st_myn":"ကွက်သစ် ၁ လမ်း"},
    {"st_eng":"Kyaung 1st Street","st_myn":"ကျောင်း ၁ လမ်း"},
    {"st_eng":"Kyaung 2nd Street","st_myn":"ကျောင်း ၂ လမ်း"},
    {"st_eng":"Kyaung 3rd Street","st_myn":"ကျောင်း ၃ လမ်း"},
    {"st_eng":"Kyaung Lane 1","st_myn":"ကျောင်းလမ်းသွယ် ၁"},
    {"st_eng":"Kyaung Lane","st_myn":"ကျောင်းလမ်း"},
    {"st_eng":"Kyaung Street","st_myn":"ကျောင်းလမ်း"},
    {"st_eng":"Kyaung Taw Yar Street","st_myn":"ကျောင်းတော်ရာလမ်း"},
    {"st_eng":"Lane 1st Street","st_myn":"လမ်းသွယ် ၁ လမ်း"},
    {"st_eng":"Lane 2nd Street","st_myn":"လမ်းသွယ် ၂ လမ်း"},
    {"st_eng":"Mahar Bandoola Street","st_myn":"မဟာဗန္ဓုလလမ်း"},
    {"st_eng":"Mandaing Street","st_myn":"မဏ္ဍိုင်လမ်း"},
    {"st_eng":"Marlar Nwe Street","st_myn":"မာလာနွယ်လမ်း"},
    {"st_eng":"Mill Road","st_myn":"စက်ရုံလမ်း"},
    {"st_eng":"Min Mahaw Street","st_myn":"မင်းမဟော်လမ်း"},
    {"st_eng":"Min Nandar Road","st_myn":"မင်းနန္ဒာလမ်း"},
    {"st_eng":"Min Nandar Street","st_myn":"မင်းနန္ဒာလမ်း"},
    {"st_eng":"Min Ye Kyaw Swar 1st Street","st_myn":"မင်းရဲကျော်စွာ ၁ လမ်း"},
    {"st_eng":"Min Ye Kyaw Swar 2nd Street","st_myn":"မင်းရဲကျော်စွာ ၂ လမ်း"},
    {"st_eng":"Min Ye Kyaw Swar 3rd Street","st_myn":"မင်းရဲကျော်စွာ ၃ လမ်း"},
    {"st_eng":"Min Ye Kyaw Swar Street","st_myn":"မင်းရဲကျော်စွာလမ်း"},
    {"st_eng":"Mingalar Theikdi Street","st_myn":"မင်္ဂလာသိဒ္ဓိလမ်း"},
    {"st_eng":"Mingalar Thiri Street","st_myn":"မင်္ဂလာသီရိလမ်း"},
    {"st_eng":"Mya Yadanar Street","st_myn":"မြရတနာလမ်း"},
    {"st_eng":"Myat Lay Nwe Street","st_myn":"မြတ်လေးနွယ်လမ်း"},
    {"st_eng":"Myittar Street","st_myn":"မေတ္တာလမ်း"},
    {"st_eng":"Myo Ma 10th Street","st_myn":"မြို့မ ၁၀ လမ်း"},
    {"st_eng":"Myo Ma 11st Street","st_myn":"မြို့မ ၁၁ လမ်း"},
    {"st_eng":"Myo Ma 11th Street","st_myn":"မြို့မ ၁၁ လမ်း"},
    {"st_eng":"Myo Ma 12nd Kannar Street","st_myn":"မြို့မ ၁၂ ကမ်းနားလမ်း"},
    {"st_eng":"Myo Ma 12th Kannar Street","st_myn":"မြို့မ ၁၂ ကမ်းနားလမ်း"},
    {"st_eng":"Myo Ma 12th Upper Street","st_myn":"မြို့မ ၁၂ အထက်လမ်း"},
    {"st_eng":"Myo Ma 13rd Street","st_myn":"မြို့မ ၁၃ လမ်း"},
    {"st_eng":"Myo Ma 13th Street","st_myn":"မြို့မ ၁၃ လမ်း"},
    {"st_eng":"Myo Ma 15th Kannar Street","st_myn":"မြို့မ ၁၅ ကမ်းနားလမ်း"},
    {"st_eng":"Myo Ma 15th Middle Street","st_myn":"မြို့မ ၁၅ အလယ်လမ်း"},
    {"st_eng":"Myo Ma 15th Upper Street","st_myn":"မြို့မ ၁၅ အထက်လမ်း"},
    {"st_eng":"Myo Ma 16th Lower Street","st_myn":"မြို့မ ၁၆ အောက်လမ်း"},
    {"st_eng":"Myo Ma 16th Upper Street","st_myn":"မြို့မ ၁၆ အထက်လမ်း"},
    {"st_eng":"Myo Ma 8th Street","st_myn":"မြို့မ ၈ လမ်း"},
    {"st_eng":"Myo Ma Lane","st_myn":"မြို့မလမ်းသွယ်"},
    {"st_eng":"Myo Ma Street","st_myn":"မြို့မလမ်း"},
    {"st_eng":"Myo Ma Strreet","st_myn":"မြို့မလမ်း"},
    {"st_eng":"Myo Pat Street","st_myn":"မြို့ပတ်လမ်း"},
    {"st_eng":"Nagar Ni 1st Street","st_myn":"နဂါးနီ ၁ လမ်း"},
    {"st_eng":"Nagar Ni 2nd Street","st_myn":"နဂါးနီ ၂ လမ်း"},
    {"st_eng":"Nagar Ni 3rd Street","st_myn":"နဂါးနီ ၃ လမ်း"},
    {"st_eng":"Nagar Ni 4th Street","st_myn":"နဂါးနီ ၄ လမ်း"},
    {"st_eng":"Nat Sin Street","st_myn":"နတ်စင်လမ်း"},
    {"st_eng":"Nawaday 1st Street","st_myn":"နဝဒေး ၁ လမ်း"},
    {"st_eng":"Nawaday Street","st_myn":"နဝဒေးလမ်း"},
    {"st_eng":"Nawarat Street","st_myn":"နဝရတ်လမ်း"},
    {"st_eng":"Nwe Ni Street","st_myn":"နွယ်နီလမ်း"},
    {"st_eng":"Padauk Street","st_myn":"ပိတောက်လမ်း"},
    {"st_eng":"Padonmar Street","st_myn":"ပဒုမ္မာလမ်း"},
    {"st_eng":"Pagoda 1st Street","st_myn":"ဘုရားလမ်း ၁ လမ်း"},
    {"st_eng":"Palae Yadanar Street","st_myn":"ပုလဲရတနာလမ်း"},
    {"st_eng":"Pathein Myae 1st Street","st_myn":"ပုသိမ်မြေ ၁ လမ်း"},
    {"st_eng":"Pathein Myae 2nd Street","st_myn":"ပုသိမ်မြေ ၂ လမ်း"},
    {"st_eng":"Pathein Myae 3rd Street","st_myn":"ပုသိမ်မြေ ၃ လမ်း"},
    {"st_eng":"Pathein Myae 4th Street","st_myn":"ပုသိမ်မြေ ၄ လမ်း"},
    {"st_eng":"Pathein Myae 5th Street","st_myn":"ပုသိမ်မြေ ၅ လမ်း"},
    {"st_eng":"Pathein Myae 6th Street","st_myn":"ပုသိမ်မြေ ၆ လမ်း"},
    {"st_eng":"Pathein Myae7th Street","st_myn":"ပုသိမ်မြေ ၇ လမ်း"},
    {"st_eng":"Pin Lon Road","st_myn":"ပင်လုံလမ်း"},
    {"st_eng":"Pin Lon Street","st_myn":"ပင်လုံလမ်း"},
    {"st_eng":"Post Office Street","st_myn":"စာတိုက်လမ်း"},
    {"st_eng":"Sabai 1st Street","st_myn":"စပယ် ၁ လမ်း"},
    {"st_eng":"Sabai 2nd Street","st_myn":"စပယ် ၂ လမ်း"},
    {"st_eng":"Sabai 3rd Street","st_myn":"စပယ် ၃ လမ်း"},
    {"st_eng":"Sabai 4th Street","st_myn":"စပယ် ၄ လမ်း"},
    {"st_eng":"Sabai 5th Street","st_myn":"စပယ် ၅ လမ်း"},
    {"st_eng":"Sabai Lane 1st","st_myn":"စပယ်လမ်းသွယ် ၁"},
    {"st_eng":"Sabai Lane 2nd","st_myn":"စပယ်လမ်းသွယ် ၂"},
    {"st_eng":"Sabai Lane 3rd","st_myn":"စပယ်လမ်းသွယ် ၃"},
    {"st_eng":"Sabai Street","st_myn":"စပယ်လမ်း"},
    {"st_eng":"Sagawar Street","st_myn":"စကားဝါလမ်း"},
    {"st_eng":"San Pya 1st Street","st_myn":"စံပြ ၁ လမ်း"},
    {"st_eng":"San Pya 2nd Street","st_myn":"စံပြ ၂ လမ်း"},
    {"st_eng":"San Pya 3rd Street","st_myn":"စံပြ ၃ လမ်း"},
    {"st_eng":"San Pya 4th Street","st_myn":"စံပြ ၄ လမ်း"},
    {"st_eng":"San Pya Street","st_myn":"စံပြလမ်း"},
    {"st_eng":"Sayar San Street","st_myn":"ဆရာစံလမ်း"},
    {"st_eng":"Seik Kan Thar Street","st_myn":"ဆိပ်ကမ်းသာလမ်း"},
    {"st_eng":"Seinta Kyaw Thu Street","st_myn":"စိန္တကျော်သူလမ်း"},
    {"st_eng":"Shwe Hnin Si Street","st_myn":"ရွှေနှင်းဆီလမ်း"},
    {"st_eng":"Shwe Hninsi Street","st_myn":"ရွှေနှင်းဆီလမ်း"},
    {"st_eng":"Shwe Nyaung Pin Street","st_myn":"ရွှေညောင်ပင်လမ်း"},
    {"st_eng":"Shwe Phu Myaw Street","st_myn":"ရွှေဖူးမျှော်လမ်း"},
    {"st_eng":"Shwe War Tun Street","st_myn":"ရွှေဝါထွန်းလမ်း"},
    {"st_eng":"Shwe Zedi Street","st_myn":"ရွှေစေတီလမ်း"},
    {"st_eng":"Swal Taw Street","st_myn":"စွယ်တော်လမ်း"},
    {"st_eng":"Sware Taw Street","st_myn":"စွယ်တော်လမ်း"},
    {"st_eng":"Ta Gun Taing Street","st_myn":"တံခွန်တိုင်လမ်း"},
    {"st_eng":"Tapin Shwe Htee Street","st_myn":"တပင်ရွှေထီးလမ်း"},
    {"st_eng":"Tapin Shwe Htee Street","st_myn":"တပင်ရွှေထီဒလမ်း"},
    {"st_eng":"Taung Phila Kyaung Street","st_myn":"တောင်ဖီလာကျောင်းလမ်း"},
    {"st_eng":"Taw Win Street","st_myn":"တော်ဝင်လမ်း"},
    {"st_eng":"Tha Khin Mya 1st Street","st_myn":"သခင်မြ ၁ လမ်း"},
    {"st_eng":"Tha Khin Mya 2nd Street","st_myn":"သခင်မြ ၂ လမ်း"},
    {"st_eng":"Tha Khin Mya 3rd Street","st_myn":"သခင်မြ ၃ လမ်း"},
    {"st_eng":"Tha Khin Mya Street","st_myn":"သခင်မြလမ်း"},
    {"st_eng":"Tha Khin Pho Hla Gyi Street","st_myn":"သခင်ဖိုးလှကြီးလမ်း"},
    {"st_eng":"Thamain Bayan Street","st_myn":"သမိန်ဗရမ်းလမ်း"},
    {"st_eng":"Thazin Nwe Street","st_myn":"သဇင်နွယ်လမ်း"},
    {"st_eng":"Thida 1st Street","st_myn":"သီတာ (၁) လမ်း"},
    {"st_eng":"Thida 1st Street","st_myn":"သီတာ ၁ လမ်း"},
    {"st_eng":"Thida 2nd Street","st_myn":"သီတာ (၂) လမ်း"},
    {"st_eng":"Thida 2nd Street","st_myn":"သီတာ ၂ လမ်း"},
    {"st_eng":"Thida Nwe Street","st_myn":"သီတာနွယ်လမ်း"},
    {"st_eng":"Thiri Yadanar Street","st_myn":"သီရိရတနာလမ်း"},
    {"st_eng":"Thitsar Nwe Street","st_myn":"သစ္စာနွယ်လမ်း"},
    {"st_eng":"Yadanar Pone Street","st_myn":"ရတနာပုံလမ်း"},
    {"st_eng":"Yadanar Theikdi Street","st_myn":"ရတနာသိဒ္ဓိလမ်း"},
    {"st_eng":"Yadanar Thiri Street","st_myn":"ရတနာသီရိလမ်း"},
    {"st_eng":"Yae Set Street","st_myn":"ရေစက်လမ်း"},
    {"st_eng":"Yamonnar Road","st_myn":"ယမုံနာလမ်း"},
    {"st_eng":"Yarza Thingyan Street","st_myn":"ရာဇသင်္ကြန်လမ်း"},
    {"st_eng":"Yuzana Street","st_myn":"ယုဇနလမ်း"},
    {"st_eng":"Ywarma Lane","st_myn":"ရွာမလမ်းသွယ်"},
    {"st_eng":"Ywarma Street","st_myn":"ရွာမလမ်း"},
    {"st_eng":"Zagawar Street","st_myn":"စကားဝါလမ်း"},
    {"st_eng":"Zawgyi Street","st_myn":"ဇော်ဂျီလမ်း"},
    {"st_eng":"Zay Street","st_myn":"ဈေးလမ်း"},
    {"st_eng":"Zayar Theikdi Street","st_myn":"ဇေယျာသိဒ္ဓိလမ်း"},
    {"st_eng":"Zayar Thiri 12nd Street","st_myn":"ဇေယျာသီရိ ၁၂ လမ်း"},
    {"st_eng":"Zayar Thiri 12th Street","st_myn":"ဇေယျာသီရိ ၁၂ လမ်း"},
    {"st_eng":"Zayar Thiri 13rd Street","st_myn":"ဇေယျာသီရိ ၁၃ လမ်း"},
    {"st_eng":"Zayar Thiri 13th Street","st_myn":"ဇေယျာသီရိ ၁၃ လမ်း"},
    {"st_eng":"Zayar Thiri 2nd Street","st_myn":"ဇေယျာသီရိ ၂ လမ်း"},
    {"st_eng":"Zayar Thiri 3rd Street","st_myn":"ဇေယျာသီရိ ၃ လမ်း"},
    {"st_eng":"Zayar Thiri 4th Street","st_myn":"ဇေယျာသီရိ ၄ လမ်း"},
    {"st_eng":"Zayar Thiri 5th Street","st_myn":"ဇေယျာသီရိ ၅ လမ်း"},
    {"st_eng":"Zayar Thiri 6th Street","st_myn":"ဇေယျာသီရိ ၆ လမ်း"},
    {"st_eng":"Zayar Thiri 7th Street","st_myn":"ဇေယျာသီရိ ၇ လမ်း"},
    {"st_eng":"Zayar Thiri Mingalar Street","st_myn":"ဇေယျာသီရိမင်္ဂလာလမ်း"},
    {"st_eng":"Zayar Thiri Street","st_myn":"ဇေယျာသီရိလမ်း"}
    	
	]
}
