{
	"Thingangyun" : [
{"st_eng":"1st Street","st_myn":"၁ လမ်း"},
{"st_eng":"2nd Street","st_myn":"၂ လမ်း"},
{"st_eng":"3rd Street","st_myn":"၃ လမ်း"},
{"st_eng":"Abu Baygar Street","st_myn":"အဘူဘေဂါလမ်း"},
{"st_eng":"Ananda Myittar Street","st_myn":"အနန္တမေတ္တာလမ်း"},
{"st_eng":"Ananda Myittar Street","st_myn":"အနန္ဒမေတ္တာလမ်း"},
{"st_eng":"Anandar Pagoda Street","st_myn":"အာနန္ဒာဘုရားလမ်း"},
{"st_eng":"Anandar Pagoda Street","st_myn":"အာနန္နာဘုရားလမ်း"},
{"st_eng":"Anawrahta 1st Street","st_myn":"အနော်ရထာ ၁ လမ်း"},
{"st_eng":"Anawrahta 2nd Street","st_myn":"အနော်ရထာ ၂ လမ်း"},
{"st_eng":"Anawrahta 3rd Street","st_myn":"အနော်ရထာ ၃ လမ်း"},
{"st_eng":"Anawrahta Street","st_myn":"အနော်ရထာလမ်း"},
{"st_eng":"Arthar Waddy Street","st_myn":"အာသာဝတီလမ်း"},
{"st_eng":"Artharwaddy Street","st_myn":"အာသာဝတီလမ်း"},
{"st_eng":"Artharwady Street","st_myn":"အာသာဝတီလမ်း"},
{"st_eng":"Arthawka Street","st_myn":"အနော်ရထာလမ်း"},
{"st_eng":"Arthawka Street","st_myn":"အာသောကလမ်း"},
{"st_eng":"Arthawka Street,","st_myn":"အနော်ရထာလမ်း"},
{"st_eng":"Athar Waddy St","st_myn":"အာသာဝတီလမ်း"},
{"st_eng":"Aung  Myay Yandanar Street","st_myn":"အောင်မြေရတနာလမ်း"},
{"st_eng":"Aung Awbar Street","st_myn":"အောင်သြဘာလမ်း"},
{"st_eng":"Aung Bawga Street","st_myn":"အောင်ဘောဂလမ်း"},
{"st_eng":"Aung Chan Thar St","st_myn":"အောင်ချမ်းသာလမ်း"},
{"st_eng":"Aung Chan Thar Street","st_myn":"အောင်ချမ်းသာလမ်း"},
{"st_eng":"Aung Mingalar Street","st_myn":"အောင်မင်္ဂလာလမ်း"},
{"st_eng":"Aung Myay Yadanar Street","st_myn":"အောင်မြေရတနာလမ်း"},
{"st_eng":"Aung Myittar Street","st_myn":"အောင်မေတ္တာလမ်း"},
{"st_eng":"Aung Seikta St","st_myn":"အောင်စိတ္တလမ်း"},
{"st_eng":"Aung Seikta Street","st_myn":"အောင်စိတ္တလမ်း"},
{"st_eng":"Aung Supan Street","st_myn":"အောင်ဆုပန်လမ်း"},
{"st_eng":"Aung Tagon Street","st_myn":"အောင်တံခွန်လမ်း"},
{"st_eng":"Aung Tha Pyae Street","st_myn":"အောင်သပြေလမ်း"},
{"st_eng":"Aung Tha Pyay 1st Street","st_myn":"အောင်သပြေ ၁ လမ်း"},
{"st_eng":"Aung Tha Pyay 2nd Street","st_myn":"အောင်သပြေ ၂ လမ်း"},
{"st_eng":"Aung Tha Pyay Street","st_myn":"အောင်သပြေလမ်း"},
{"st_eng":"Aung Thapyae 1st Street","st_myn":"အောင်သရဖီ ၁ လမ်း"},
{"st_eng":"Aung Thapyae 2nd Street","st_myn":"အောင်သရဖီ ၂ လမ်း"},
{"st_eng":"Aung Thapyae St","st_myn":"ခရေမြိုင်လမ်း"},
{"st_eng":"Aung Thapyae St","st_myn":"အောင်သပြေလမ်း"},
{"st_eng":"Aung Thapyae Street","st_myn":"အောင်သရဖီလမ်း"},
{"st_eng":"Aung Thukha Street","st_myn":"အောင်သုခလမ်း"},
{"st_eng":"Aung Yadanar Street","st_myn":"အောင်ရတနာလမ်း"},
{"st_eng":"Aung Zaya 1st Street","st_myn":"အောင်ဇေယျ ၁ လမ်း"},
{"st_eng":"Aung Zaya 2nd Street","st_myn":"အောင်ဇေယျ ၂ လမ်း"},
{"st_eng":"Aung Zaya 3rd Street","st_myn":"အောင်ဇေယျ ၃ လမ်း"},
{"st_eng":"Aung Zaya 4th Street","st_myn":"အောင်ဇေယျ ၄ လမ်း"},
{"st_eng":"Aung Zaya 5th Street","st_myn":"အောင်ဇေယျ ၅ လမ်း"},
{"st_eng":"Aung Zaya 6th Street","st_myn":"အောင်ဇေယျ ၆ လမ်း"},
{"st_eng":"Aung Zaya 7th Street","st_myn":"အောင်ဇေယျ ၇ လမ်း"},
{"st_eng":"Aung Zaya 8th Street","st_myn":"အောင်ဇေယျ ၈ လမ်း"},
{"st_eng":"Aung Zaya Street","st_myn":"အောင်ဇေယျလမ်း"},
{"st_eng":"Awaiyar 1st Street","st_myn":"အဝေရာ ၁ လမ်း"},
{"st_eng":"Awaiyar 2nd Street","st_myn":"အဝေရာ ၂ လမ်း"},
{"st_eng":"Awaiyar Street","st_myn":"အဝေရာလမ်း"},
{"st_eng":"Aye Myittar Street","st_myn":"အေးမေတ္တာလမ်း"},
{"st_eng":"Aye Yadanar Street","st_myn":"အေးရတနာလမ်း"},
{"st_eng":"Aye Yeik Thar Kyaung Street","st_myn":"အောင်ရိပ်သာကျောင်းလမ်း"},
{"st_eng":"Bandoola Street","st_myn":"ဗန္ခ္ဓုလလမ်း"},
{"st_eng":"Bandoola Street","st_myn":"ဗန္ဓုလလမ်း"},
{"st_eng":"Baw Sin Street","st_myn":"ဘောစင်လမ်း"},
{"st_eng":"Bawa Myint Street","st_myn":"ဘဝမြင့်လမ်း"},
{"st_eng":"Bawga 1st Street","st_myn":"ဘောဂ ၁ လမ်း"},
{"st_eng":"Bawga 2nd Street","st_myn":"ဘောဂ ၂ လမ်း"},
{"st_eng":"Bawga Street","st_myn":"ဘောဂလမ်း"},
{"st_eng":"Bawga Zay Street","st_myn":"ဘောဂဈေးလမ်း"},
{"st_eng":"Bayint Naung 10th Street","st_myn":"ဘုရင့်နောင် ၁၀ လမ်း"},
{"st_eng":"Bayint Naung 11st Street","st_myn":"ဘုရင့်နောင် ၁၁ လမ်း"},
{"st_eng":"Bayint Naung 11th Street","st_myn":"ဘုရင့်နောင် ၁၁ လမ်း"},
{"st_eng":"Bayint Naung 12nd Street","st_myn":"ဘုရင့်နောင် ၁၂ လမ်း"},
{"st_eng":"Bayint Naung 12th Street","st_myn":"ဘုရင့်နောင် ၁၂ လမ်း"},
{"st_eng":"Bayint Naung 13rd Street","st_myn":"ဘရင့်နောင် ၁၃ လမ်း"},
{"st_eng":"Bayint Naung 13th Street","st_myn":"ဘုရင့်နောင် ၁၃ လမ်း"},
{"st_eng":"Bayint Naung 14th Street","st_myn":"ဘုရင့်နောင် ၁၄ လမ်း"},
{"st_eng":"Bayint Naung 15th Street","st_myn":"ဘုရငသ့်နောင်(၁၅)လမ်း"},
{"st_eng":"Bayint Naung 15th Street","st_myn":"ဘုရင့်နောင် ၁၅ လမ်း"},
{"st_eng":"Bayint Naung 16th Street","st_myn":"ဘုရင့်နောင် ၁၆ လမ်း"},
{"st_eng":"Bayint Naung 17th Street","st_myn":"ဘုရင့်နောင် ၁၇ လမ်း"},
{"st_eng":"Bayint Naung 18th Street","st_myn":"ဘုရင့်နောင် ၁၈ လမ်း"},
{"st_eng":"Bayint Naung 1st Street","st_myn":"ဘုရင့်နောင် ၁ လမ်း"},
{"st_eng":"Bayint Naung 2nd Street","st_myn":"ဘုရင့်နောင် ၂ လမ်း"},
{"st_eng":"Bayint Naung 3rd Street","st_myn":"ဘုရင့်နောင် ၃ လမ်း"},
{"st_eng":"Bayint Naung 9th Lane","st_myn":"ဘရင့်နောင် ၉ လမ်းသွယ်"},
{"st_eng":"Bayint Naung 9th Street","st_myn":"ဘရင့်နောင် ၉ လမ်း"},
{"st_eng":"Bayint Naung 9th Street","st_myn":"ဘုရင့်နောင် ၉ လမ်း"},
{"st_eng":"Bayint Naung Lane (1)","st_myn":"ဘုရင့်နောင်လမ်းသွယ်၁လမ်း"},
{"st_eng":"Bayint Naung Lane (2)","st_myn":"ဘုရင့်နောင်လမ်းသွယ်၂လမ်း"},
{"st_eng":"Bayint Naung Lane 1","st_myn":"ဘုရင့်နောင်လမ်းသွယ် ၁"},
{"st_eng":"Bayint Naung Lane 2","st_myn":"ဘုရင့်နောင်လမ်းသွယ် ၂"},
{"st_eng":"Bayint Naung Lane 9","st_myn":"ဘုရင့်နောင်လမ်းသွယ် ၉"},
{"st_eng":"Bayint Naung Street","st_myn":"ဘုရင့်နောင်လမ်း"},
{"st_eng":"Bo Aung Kyaw Street","st_myn":"ဗိုလ်အောင်ကျော်လမ်း"},
{"st_eng":"Bo Kan Nyunt Street","st_myn":"ဗိုလ်ကံညွန့်လမ်း"},
{"st_eng":"Bo Kan Nyunt Street","st_myn":"ဗိုလ်ကန်ညွန့်လမ်း"},
{"st_eng":"Bo Tayza 1st Street","st_myn":"ဗိုလ်တေဇ ၁ လမ်း"},
{"st_eng":"Bo Tayza 2nd Street","st_myn":"ဗိုလ်တေဇ ၂ လမ်း"},
{"st_eng":"Bo Tayza 3rd Street","st_myn":"ဗိုလ်တေဇ ၃ လမ်း"},
{"st_eng":"Bo Tayza 3th Street","st_myn":"ဗိုလ်တေဇ ၃ လမ်း"},
{"st_eng":"Bo Tayza 4th Street","st_myn":"ဗိုလ်တေဇ ၄ လမ်း"},
{"st_eng":"Chan Aye Street","st_myn":"ချမ်းအေးလမ်း"},
{"st_eng":"Cherry Street","st_myn":"ချယ်ရီလမ်း"},
{"st_eng":"Chin Dwin Street","st_myn":"ချင်းတွင်းလမ်း"},
{"st_eng":"Chue 1st Street","st_myn":"ချူး ၁ လမ်း"},
{"st_eng":"Chue 2nd Street","st_myn":"ချူး ၂ လမ်း"},
{"st_eng":"Dana Aung Street","st_myn":"ဓနအောင်လမ်း"},
{"st_eng":"Dana Aung Street","st_myn":"နအောင်လမ်း"},
{"st_eng":"Dana Theikdi Street","st_myn":"ဓနသိဒ္ဓိလမ်း"},
{"st_eng":"Dana Theikdi Street","st_myn":"ဓနသိဒ္ဓ္ဓိလမ်း"},
{"st_eng":"Dana Theikdi Street","st_myn":"နသိဒ္ဓိလမ်း"},
{"st_eng":"Dawna Street","st_myn":"ဒေါနလမ်း"},
{"st_eng":"Dhama Lawka Kyaung  Street","st_myn":"ဓမ္မလောကကျောင်းလမ်း"},
{"st_eng":"Dhama Lawka Kyaung Street","st_myn":"ဓမ္မလောကကျောင်းလမ်း"},
{"st_eng":"Dhamar Yon Street","st_myn":"ဓမ္မာရုံလမ်း"},
{"st_eng":"Eiksarthara Street","st_myn":"ဣစ္ဆာသယလမ်း"},
{"st_eng":"Eiksietan Street","st_myn":"ဣစိတံလမ်း"},
{"st_eng":"Eiksietan Street","st_myn":"ဣစ္ဆိတံလမ်း"},
{"st_eng":"Extension 3 Street","st_myn":"တိုးချဲ့ ၃ လမ်း"},
{"st_eng":"Extension 3rd Street","st_myn":"တိုးချဲ့ ၃ လမ်း"},
{"st_eng":"Extension 4 Street","st_myn":"တိုးချဲ့ ၄ လမ်း"},
{"st_eng":"Extension 4th Street","st_myn":"တိုးချဲ့ ၄ လမ်း"},
{"st_eng":"Extension 5 Street","st_myn":"တိုးချဲ့ ၄ လမ်း"},
{"st_eng":"Extension 5th Street","st_myn":"တိုးချဲ့ ၅ လမ်း"},
{"st_eng":"Gamone Street","st_myn":"ဂမုန်းလမ်း"},
{"st_eng":"Gandamar Street","st_myn":"ဂန္ဓမာလမ်း"},
{"st_eng":"Gant Gaw Myaing Street","st_myn":"ကံ့ကော်မြိုင်လမ်း"},
{"st_eng":"Gantgaw Myaing 1st Street","st_myn":"ကံ့ကော်မြိုင် ၁ လမ်း"},
{"st_eng":"Gantgaw Myaing 1st Street","st_myn":"ကံ့ကော်မြိုင်(၁)လမ်း"},
{"st_eng":"Gantgaw Myaing 2nd Street","st_myn":"ကံ့ကော်မြိုင် ၂ လမ်း"},
{"st_eng":"Gantgaw Myaing 2nd Street","st_myn":"ကံ့ကော်မြိုင်(၂)လမ်း"},
{"st_eng":"Gantgaw Myaing 3rd Street","st_myn":"ကံ့ကော်မြိုင် ၃ လမ်း"},
{"st_eng":"Gantgaw Myaing 3rd Street","st_myn":"ကံ့ကော်မြိုင်(၃)လမ်း"},
{"st_eng":"Gantgaw Myaing Street","st_myn":"ကံ့ကော်မြိုင်လမ်း"},
{"st_eng":"Gantgaw Street","st_myn":"ကံ့ကော်လမ်း"},
{"st_eng":"Gantgaw Yeik Thar Street","st_myn":"ကံ့ကော်ရိပ်သာလမ်း"},
{"st_eng":"Hinn Thar Street","st_myn":"ဟင်္သာလမ်း"},
{"st_eng":"Hinthar Street","st_myn":"ဟင်္သာလမ်း"},
{"st_eng":"Hninsi Gone Street","st_myn":"နှင်းဆီကုန်းလမ်း"},
{"st_eng":"Hninsi Ni Street","st_myn":"နှင်းဆီနီလမ်း"},
{"st_eng":"Hninsi Phyu Street","st_myn":"နှင်းဆီဖြူလမ်း"},
{"st_eng":"Hninsi Street","st_myn":"နှင်းဆီလမ်း"},
{"st_eng":"Hninsi War Street","st_myn":"နှင်းဆီဝါလမ်း"},
{"st_eng":"Independence Lane","st_myn":"လွပ်လပ်ရေးလမ်းသွယ်"},
{"st_eng":"Independence St","st_myn":"လွတ်လပ်ရေးလမ်း"},
{"st_eng":"Independence Street","st_myn":"လွတ်လပ်ရေးလမ်း"},
{"st_eng":"Ingyin Myaing 1st Street","st_myn":"အင်ကြင်းမြိုင် ၁ လမ်း"},
{"st_eng":"Ingyin Myaing 2nd Street","st_myn":"အင်ကြင်းမြိုင် ၂ လမ်း"},
{"st_eng":"Ingyin Myaing 3rd Street","st_myn":"အင်ကြင်းမြိုင် ၃ လမ်း"},
{"st_eng":"Ingyin Myaing 4th Street","st_myn":"အင်ကြင်းမြိုင် ၄ လမ်း"},
{"st_eng":"Ingyin Myaing 5th Street","st_myn":"အင်ကြင်းမြိုင် ၅ လမ်း"},
{"st_eng":"Ingyin Myaing Street","st_myn":"အင်းကြင်းမြိုင်လမ်း"},
{"st_eng":"Ingyin Myaing Street","st_myn":"အင်ကြင်းမြိုင်လမ်း"},
{"st_eng":"Ingyin Street","st_myn":"အင်ကြင်းလမ်း"},
{"st_eng":"Inngyin Mying Street","st_myn":"အင်းကြင်းမြိုင်လမ်း"},
{"st_eng":"Kamar Kyi Road","st_myn":"ကမာကြည်လမ်း"},
{"st_eng":"Kamar Street (East)","st_myn":"ကမာလမ်း(အရှေ့)"},
{"st_eng":"Kamar Street (West)","st_myn":"ကမာလမ်း(အနောက်)"},
{"st_eng":"Kamar(East) Street","st_myn":"ကမာလမ်း(အရှေ့)"},
{"st_eng":"Kamar(East) Street","st_myn":"ပယင်းလမ်း(အရှေ့)"},
{"st_eng":"Kamar(West) Street","st_myn":"ကမာလမ်း(အနောက်)"},
{"st_eng":"Kan Oo Street","st_myn":"ကန်ဦးလမ်း"},
{"st_eng":"Kan Taw Street","st_myn":"ကန်တော်လမ်း"},
{"st_eng":"Kan Thar Yar Street","st_myn":"ကန်သာယာလမ်း"},
{"st_eng":"Kan Thayar Street","st_myn":"ကန်သာယာလမ်း"},
{"st_eng":"Kannar Street","st_myn":"ကမ်းနားလမ်း"},
{"st_eng":"Kathit Myaing Street","st_myn":"ကသစ်မြိုင်လမ်း"},
{"st_eng":"Kauk Lae 1st Street","st_myn":"ကောက်လဲ့ ၁ လမ်း"},
{"st_eng":"Kauk Lae 2nd Street","st_myn":"ကောက်လဲ့ ၂ လမ်း"},
{"st_eng":"Kauk Lae 3rd Street","st_myn":"ကောက်လဲ့ ၃ လမ်း"},
{"st_eng":"Kauk Lae 4th Street","st_myn":"ကောက်လဲ့ ၄ လမ်း"},
{"st_eng":"Kauk Lyin Street","st_myn":"ကောက်လျင်လမ်း"},
{"st_eng":"Kauk Saw Street","st_myn":"ကောက်စောလမ်း"},
{"st_eng":"Kaymar Street","st_myn":"ခေမာလမ်း"},
{"st_eng":"Khaing Marlar Street","st_myn":"ခိုင်မာလာလမ်း"},
{"st_eng":"Khaing Thazin Street","st_myn":"ခိုင်သဇင်လမ်း"},
{"st_eng":"Khay Mar Thi 3rd Lane","st_myn":"ခေမာသီလမ်းသွယ် ၃ လမ်း"},
{"st_eng":"Khay Mar Thi Lane 1","st_myn":"ခေမာသီလမ်းသွယ် ၁"},
{"st_eng":"Khay Mar Thi Lane 1st Street","st_myn":"ခေမာသီလမ်းသွယ် ၁"},
{"st_eng":"Khay Mar Thi Lane 2","st_myn":"ခေမာသီလမ်းသွယ် ၂"},
{"st_eng":"Khay Mar Thi Lane 2nd Street","st_myn":"ခေမာသီလမ်းသွယ် ၂"},
{"st_eng":"Khay Mar Thi Lane 3","st_myn":"ခေမာသီလမ်းသွယ် ၃"},
{"st_eng":"Khay Mar Thi Lane 3rd Street","st_myn":"ခေမာသီလမ်းသွယ် ၃"},
{"st_eng":"Khay Mar Thi Street","st_myn":"ခေမာသီလမ်း"},
{"st_eng":"Khayae Myaing Lane Street","st_myn":"ခရေမြိုင်လမ်းသွယ်"},
{"st_eng":"Khayae Myaing Lane","st_myn":"ခရေမြိုင်လမ်းသွယ်"},
{"st_eng":"Khayae Myaing Street","st_myn":"ခရေမြိုင်လမ်း"},
{"st_eng":"Khayae Pin Street","st_myn":"ခရေပင်လမ်း"},
{"st_eng":"Khayae Street","st_myn":"ခရေလမ်း"},
{"st_eng":"Khaymar Road.","st_myn":"ခေမာလမ်း"},
{"st_eng":"Khaymar Street","st_myn":"ခေမာလမ်း"},
{"st_eng":"Khun Ni 1st Street","st_myn":"ခွန်နီ ၁ လမ်း"},
{"st_eng":"Khun Ni 2nd Street","st_myn":"ခွန်နီ ၂ လမ်း"},
{"st_eng":"Khun Ni 3rd Street","st_myn":"ခွန်နီ ၃ လမ်း"},
{"st_eng":"Khun Ni Street","st_myn":"ခွန်နီလမ်း"},
{"st_eng":"Kyaikasan Pagoda Road","st_myn":"ကျိုက္ကဆံဘုရားလမ်း"},
{"st_eng":"Kyan Sit Thar Street","st_myn":"ကျန်စစ်သားလမ်း"},
{"st_eng":"Kyauk Sein Street","st_myn":"ကျောက်စိမ်းလမ်း"},
{"st_eng":"Kyaung Street","st_myn":"ကျောင်းလမ်း"},
{"st_eng":"Kyi Su Kyaung Street","st_myn":"ကျီစုကျောင်းလမ်း"},
{"st_eng":"Kyoe Set Lane Street","st_myn":"ကြိုးစက်လမ်းသွယ်"},
{"st_eng":"Kyoe Set Lane","st_myn":"ကြိုးစက်လမ်းသွယ်"},
{"st_eng":"Kyoe Set Yone Street","st_myn":"ကြိုးစက်ရုံလမ်း"},
{"st_eng":"Kyun Shwe Myaing Lane (1)","st_myn":"ကျွန်းရွှေမြိုင်လမ်းသွယ် (၁)"},
{"st_eng":"Kyun Shwe Myaing Lane (2)","st_myn":"ကျွန်းရွှေမြိုင်လမ်းသွယ် (၂)"},
{"st_eng":"Kyun Shwe Myaing Lane 1","st_myn":"ကျွန်းရွှေမြိုင်လမ်းသွယ် ၁"},
{"st_eng":"Kyun Shwe Myaing Lane 2","st_myn":"ကျွန်းရွှေမြိုင်လမ်းသွယ် ၂"},
{"st_eng":"Kyun Shwe Myaing Lane","st_myn":"ကျွန်းရွှေမြိုင်လမ်းသွယ်"},
{"st_eng":"Kyun Shwe Myaing Street","st_myn":"ကျွန်းရွှေမြိုင်လမ်း"},
{"st_eng":"Lay Daung Kan Road","st_myn":"လေးထောင့်ကန်လမ်း"},
{"st_eng":"Lay Daunt Kan Road","st_myn":"လေးထောင့်ကန်လမ်း"},
{"st_eng":"Lone Thwe Street","st_myn":"လုံးသွယ်လမ်း"},
{"st_eng":"Lote Thar Lane","st_myn":"လုပ်သားလမ်းသွယ်"},
{"st_eng":"Lote Thar Street","st_myn":"လုပ်သားလမ်း"},
{"st_eng":"Mahar Bandoola Street","st_myn":"မဟာဗန္ဓုလလမ်း"},
{"st_eng":"Mahaw Gani Street","st_myn":"မဟော်ဂနီလမ်း"},
{"st_eng":"Marlar Myaing Street","st_myn":"မာလာမြိုင်လမ်း"},
{"st_eng":"May Gha Wadi Kyaung Street","st_myn":"မေဃဝတီကျောင်းလမ်း"},
{"st_eng":"May Kha Lane 1","st_myn":"မေခလမ်းသွယ် ၁"},
{"st_eng":"May Kha Lane 3","st_myn":"မေခလမ်းသွယ် ၃"},
{"st_eng":"May Kha Street","st_myn":"မေခလမ်း"},
{"st_eng":"Mee Done Street","st_myn":"မီးဒုံးလမ်း"},
{"st_eng":"Mee Done Street","st_myn":"အောင်ဇေယျလမ်း"},
{"st_eng":"Mercury Street","st_myn":"မာကျူရီလမ်း"},
{"st_eng":"Miba Myinttar Lane 2","st_myn":"မိဘမေတ္တာလမ်းသွယ် ၂"},
{"st_eng":"Miba Myittar Lane 2","st_myn":"မိဘမေတ္တာလမ်းသွယ် ၂"},
{"st_eng":"Min Din Street","st_myn":"မင်းဒင်လမ်း"},
{"st_eng":"Min Ye Kyaw Swar Street","st_myn":"မင်းရဲကျော်စွာလမ်း"},
{"st_eng":"Mingalar Street","st_myn":"မင်္ဂလာလမ်း"},
{"st_eng":"Mingalar Yeik Thar Street","st_myn":"မင်္ဂလာရိပ်သာလမ်း"},
{"st_eng":"Mingalar Yeikthar Street","st_myn":"မင်္ဂလာရိပ်သာလမ်း"},
{"st_eng":"Moe Makha 1st Lane.","st_myn":"မိုးမခ ၁ လမ်း"},
{"st_eng":"Moe Makha 1st Street","st_myn":"မိုးမခ ၁ လမ်း"},
{"st_eng":"Moe Makha 2nd Lane.","st_myn":"မိုးမခ ၂ လမ်း"},
{"st_eng":"Moe Makha 2nd Street","st_myn":"မိုးမခ ၂ လမ်း"},
{"st_eng":"Moe Makha 3rd Lane.","st_myn":"မိုးမခ ၃ လမ်း"},
{"st_eng":"Moe Makha 3rd Street","st_myn":"မိုးမခ ၃ လမ်း"},
{"st_eng":"Moe Makha Street","st_myn":"မိုးမခလမ်း"},
{"st_eng":"Mya Thida Street","st_myn":"မြသီတာလမ်း"},
{"st_eng":"Mya Waddy Lane","st_myn":"မြဝတီလမ်းသွယ်"},
{"st_eng":"Mya Waddy Street","st_myn":"မြဝတီလမ်း"},
{"st_eng":"Mya Wut Yi Street","st_myn":"မြဝတ်ရည်လမ်း"},
{"st_eng":"Myat Pan Wut Yi Street","st_myn":"မြတ်ပန်းဝတ်ရည်လမ်း"},
{"st_eng":"Myawaddy Street","st_myn":"မြဝတီလမ်း"},
{"st_eng":"Myintzu Street","st_myn":"မဉ္ဇူလမ်း"},
{"st_eng":"Myittar 2nd Street","st_myn":"မေတ္တာ ၂ လမ်း"},
{"st_eng":"Myittar 3rd Street","st_myn":"မေတ္တာ ၃ လမ်း"},
{"st_eng":"Myittar Street","st_myn":"မေတ္တာလမ်း"},
{"st_eng":"Nat Sin 3 Street","st_myn":"နတ်စင် ၃ လမ်း"},
{"st_eng":"Nat Sin 3rd Street","st_myn":"နတ်စင် ၃ လမ်း"},
{"st_eng":"Nat Sin 4th Street","st_myn":"နတ်စင် ၄ လမ်း"},
{"st_eng":"Nat Sin 5th Street","st_myn":"နတ်စင် ၅ လမ်း"},
{"st_eng":"Nat Sin Street","st_myn":"နတ်စင်လမ်း"},
{"st_eng":"Nawarat Lane 1","st_myn":"နဝရတ်လမ်းသွယ် ၁"},
{"st_eng":"Nawarat Lane 2","st_myn":"နဝရတ်လမ်းသွယ် ၂"},
{"st_eng":"Nawarat Lane","st_myn":"နဝရတ်လမ်း"},
{"st_eng":"Nawarat Lane","st_myn":"နဝရတ်လမ်းသွယ်"},
{"st_eng":"Nawarat Street","st_myn":"နဝရတ်လမ်း"},
{"st_eng":"Nga Moe Yeik  8th Street","st_myn":"ငမိုးရိပ် ၈ လမ်း"},
{"st_eng":"Nga Moe Yeik 10th Street","st_myn":"ငမိုးရိပ် ၁၀ လမ်း"},
{"st_eng":"Nga Moe Yeik 2nd Street","st_myn":"ငမိုးရိပ် ၂ လမ်း"},
{"st_eng":"Nga Moe Yeik 3rd Street","st_myn":"ငမိုးရိပ် ၃ လမ်း"},
{"st_eng":"Nga Moe Yeik 4th Street","st_myn":"ငမိုးရိပ် ၄ လမ်း"},
{"st_eng":"Nga Moe Yeik 5th Street","st_myn":"ငမိုးရိပ် ၅ လမ်း"},
{"st_eng":"Nga Moe Yeik 6th Street","st_myn":"ငမိုးရိပ် ၆ လမ်း"},
{"st_eng":"Nga Moe Yeik 7th Street","st_myn":"ငမိုးရိပ် ၇ လမ်း"},
{"st_eng":"Nga Moe Yeik 8th Street","st_myn":"ငမိုးရိပ် ၈ လမ်း"},
{"st_eng":"Nga Moe Yeik 9th Street","st_myn":"ငမိုးရိပ် ၉ လမ်း"},
{"st_eng":"Ngu Shwe Myaing Kyaung Street","st_myn":"ငုရွှေမြိုင်ကျောင်းလမ်း"},
{"st_eng":"Ngu War 1st Street","st_myn":"ငုဝါ ၁ လမ်း"},
{"st_eng":"Ngu War 3rd Street","st_myn":"ငုဝါ ၃ လမ်း"},
{"st_eng":"Ngu War 4th Street","st_myn":"ငုဝါ ၄ လမ်း"},
{"st_eng":"Ngu War Street","st_myn":"ငုဝါလမ်း"},
{"st_eng":"Ngwe Pyi Thar Yeik Thar Street","st_myn":"ငွေပြည်သာရိပ်သာလမ်း"},
{"st_eng":"Nilar Street (East)","st_myn":"နီလာလမ်း (အရှေ့)"},
{"st_eng":"Nilar Street (West)","st_myn":"နီလာလမ်း (အနောက်)"},
{"st_eng":"Nilar Street","st_myn":"နီလာလမ်း"},
{"st_eng":"Nilar(East) Street","st_myn":"နီလာလမ်း(အရှေ့)"},
{"st_eng":"Nilar(West) Street","st_myn":"နီလာလမ်း(အနောက်)"},
{"st_eng":"Nwe Ni Street","st_myn":"နွယ်နီလမ်း"},
{"st_eng":"Nwe Thargi Street","st_myn":"နွယ်သာကီလမ်း"},
{"st_eng":"Nwe Thargi Street","st_myn":"နွယ်သာဂီလမ်း"},
{"st_eng":"Nwethargi Street","st_myn":"နွယ်သာဂီလမ်း"},
{"st_eng":"Nyarti Lane","st_myn":"ညာတိလမ်သွယ်"},
{"st_eng":"Nyarti Street","st_myn":"ညာတိလမ်း"},
{"st_eng":"Nyaung Ai Street","st_myn":"ညောင်အိုင်လမ်း"},
{"st_eng":"Oakbo Street","st_myn":"အုတ်ဘိုလမ်း"},
{"st_eng":"Oh Bo Street","st_myn":"အိုဘိုလမ်း"},
{"st_eng":"Okkalar Oo Phayar Street","st_myn":"ဥက္ကလာဦးဘုရားလမ်း"},
{"st_eng":"Ou Yin St","st_myn":"ဥယျဉ်လမ်း"},
{"st_eng":"Ou Yin St","st_myn":"ဥယျာဉ်လမ်း"},
{"st_eng":"Ou Yin Street","st_myn":"ဥယျာဉ်လမ်း"},
{"st_eng":"Pa Yin Street (East)","st_myn":"ပယင်းလမ်း (အရှေ့)"},
{"st_eng":"Pa Yin(East) Street","st_myn":"ပယင်းလမ်း(အရှေ့)"},
{"st_eng":"Padamyar Street","st_myn":"ပတ္တမြားလမ်း"},
{"st_eng":"Padauk Myaing Street","st_myn":"ပိတောက်မြိုင်လမ်း"},
{"st_eng":"Padauk Street","st_myn":"ပိတောက်လမ်း"},
{"st_eng":"Padonmar Street","st_myn":"ပဒုမ္မာလမ်း"},
{"st_eng":"Palae Street (East)","st_myn":"ပုလဲလမ်း (အရှေ့)"},
{"st_eng":"Palae Street (West)","st_myn":"ပုလဲလမ်း (အနောက်)"},
{"st_eng":"Palae(East) Street","st_myn":"ပုလဲလမ်း(အရှေ့)"},
{"st_eng":"Palae(West) Street","st_myn":"ပုလဲလမ်း(အနောက်)"},
{"st_eng":"Pan Maezali Street","st_myn":"ပန်းမယ်ဇလီလမ်း"},
{"st_eng":"Pan Tra Street","st_myn":"ပန်တျာလမ်း"},
{"st_eng":"Pan War Street","st_myn":"ပန်းဝါလမ်း"},
{"st_eng":"Pan Yike Street","st_myn":"ပန်းရိုက်လမ်း"},
{"st_eng":"Paw San Hmwe 1st Street","st_myn":"ပေါ်ဆန်းမွှေး ၁ လမ်း"},
{"st_eng":"Paw San Hmwe 2nd Street","st_myn":"ပေါ်ဆန်းမွှေး ၂ လမ်း"},
{"st_eng":"Paw San Hmwe 3rd Street","st_myn":"ပေါ်ဆန်းမွှေး ၃ လမ်း"},
{"st_eng":"Paw San Hmwe 4th Street","st_myn":"ပေါ်ဆန်းမွှေး ၄ လမ်း"},
{"st_eng":"Paw San Hmwe 5th Street","st_myn":"ပေါ်ဆန်းမွှေ(၅)လမ်း"},
{"st_eng":"Paw San Hmwe 5th Street","st_myn":"ပေါ်ဆန်းမွှေး ၅ လမ်း"},
{"st_eng":"Paw San Hmwe 6th Street","st_myn":"ပေါ်ဆန်းမွှေး ၆ လမ်း"},
{"st_eng":"Paw San Hmwe 7th Street","st_myn":"ပေါ်ဆန်းမွှေး ၇ လမ်း"},
{"st_eng":"Paw San Hmwe 8th Street","st_myn":"ပေါ်ဆန်းမွှေး ၈ လမ်း"},
{"st_eng":"Paw San Hmwe Street","st_myn":"ပေါ်ဆန်းမွှေးလမ်း"},
{"st_eng":"Paya Thone Suu Kyaung Street","st_myn":"ဘုရားသုံးဆူကျောင်းလမ်း"},
{"st_eng":"Phayar Thone Suu Kyaung Street","st_myn":"ဘုရားသုံးဆူကျောင်းလမ်း"},
{"st_eng":"Pin Lon 1st Street","st_myn":"ပင်လုံ ၁ လမ်း"},
{"st_eng":"Pin Lon 2nd Street","st_myn":"ပင်လုံ ၂ လမ်း"},
{"st_eng":"Pin Lon 3rd Street","st_myn":"ပင်လုံ ၃ လမ်း"},
{"st_eng":"Pin Lon Pat Street","st_myn":"ပင်လုံပတ်လမ်း"},
{"st_eng":"Pin Lon Road.","st_myn":"ပင်လုံလမ်း"},
{"st_eng":"Popa Yone Kyaung Street","st_myn":"ပုပ္ပါရုံကျောင်းလမ်း"},
{"st_eng":"Pyi  Thar Yar Street","st_myn":"ပြည်သာယာလမ်း"},
{"st_eng":"Pyi Htaung Su Road","st_myn":"ပြည်ထောင်စုလမ်း"},
{"st_eng":"Pyi Htaung Su Street","st_myn":"ပြည်ထောင်စုလမ်း"},
{"st_eng":"Pyi Taw Aye Street","st_myn":"ပြည်တော်အေးလမ်း"},
{"st_eng":"Pyi Taw Thar Street","st_myn":"ပြည်တော်သာလမ်း"},
{"st_eng":"Pyi Thar Yar Street","st_myn":"ပြည်သာယာလမ်း"},
{"st_eng":"Pyinma Myaing (Su Paung) Street","st_myn":"ပျဉ်းမမြိုင်လမ်း (စုပေါင်း)"},
{"st_eng":"Pyinma Myaing Street","st_myn":"ပျဉ်းမမြိုင်လမ်း"},
{"st_eng":"Pyinmanar Street","st_myn":"ပျဉ်းမနားလမ်း"},
{"st_eng":"Pyon Street","st_myn":"ပြွန်လမ်း"},
{"st_eng":"Sabai Phyu St","st_myn":"စံပယ်ဖြူလမ်း"},
{"st_eng":"Sabai Phyu Street","st_myn":"စပယ်ဖြူလမ်း"},
{"st_eng":"San Pya 1st Street","st_myn":"စံပြ ၁ လမ်း"},
{"st_eng":"San Pya 2nd Street","st_myn":"စံပြ ၂ လမ်း"},
{"st_eng":"San Pya 3rd Street","st_myn":"စံပြ ၃ လမ်း"},
{"st_eng":"San Pya 4th Street","st_myn":"စံပြ ၄ လမ်း"},
{"st_eng":"San Pya 5th Street","st_myn":"စံပြ ၅ လမ်း"},
{"st_eng":"San Pya 6th Street","st_myn":"စံပြ ၆ လမ်း"},
{"st_eng":"San Pya 7th Street","st_myn":"စံပြ ၇ လမ်း"},
{"st_eng":"San Pya 8th Street","st_myn":"စံပြ ၈ လမ်း"},
{"st_eng":"San Pya Hospital Street","st_myn":"စံပြဆေးရုံလမ်း"},
{"st_eng":"Sandagu Street","st_myn":"စန္ဒကူးလမ်း"},
{"st_eng":"Sayee Pin Street","st_myn":"စရည်းပင်လမ်း"},
{"st_eng":"Seikta Thukha Street","st_myn":"စိတ္တသုခလမ်း"},
{"st_eng":"Sein Pan Myaing Street","st_myn":"စိန်ပန်းမြိုင်လမ်း"},
{"st_eng":"Sein Pan Street","st_myn":"စိန်ပန်းလမ်း"},
{"st_eng":"Shin Saw Pu Street","st_myn":"ရှင်စောပုလမ်း"},
{"st_eng":"Shwe Nyar Myae Street","st_myn":"ရွှေညာမြေလမ်း"},
{"st_eng":"Shwe Nyaung Pin Street","st_myn":"ရွှေညောင်ပင်လမ်း"},
{"st_eng":"Shwe War Street","st_myn":"ရွှေဝါလမ်း"},
{"st_eng":"Shwe War Tun Street","st_myn":"ရွှေဝါထွန်းလမ်း"},
{"st_eng":"Swal Taw Street","st_myn":"စွယ်တော်လမ်း"},
{"st_eng":"Tapin Shwe Htee Street","st_myn":"တပင်ရွှေထီးလမ်း"},
{"st_eng":"Taung Htate Pan Street","st_myn":"တောင်ထိပ်ပန်းလမ်း"},
{"st_eng":"Tha Khin Pho Hla Gyi Street","st_myn":"သခင်ဖိုးလှကြီးလမ်း"},
{"st_eng":"Tha Khin Pho Hla Street","st_myn":"သခင်ဖိုးလှလမ်း"},
{"st_eng":"Tha Pyay Nyo Street","st_myn":"သပြေညိုလမ်း"},
{"st_eng":"Thamadi 1st Street","st_myn":"သမာဓိ ၁ လမ်း"},
{"st_eng":"Thamadi 2nd Street","st_myn":"သမာဓိ ၂ လမ်း"},
{"st_eng":"Thamadi 3rd Street","st_myn":"သမာဓိ ၃ လမ်း"},
{"st_eng":"Thamadi 4th Street","st_myn":"သမာဓိ ၄ လမ်း"},
{"st_eng":"Thamadi 5th Street","st_myn":"သမာဓိ ၅ လမ်း"},
{"st_eng":"Thamain Bayan 1st Street","st_myn":"သမိန်ဗရမ်း ၁ လမ်း"},
{"st_eng":"Thamain Bayan 2nd Street","st_myn":"သမိန်ဗရမ်း ၂ လမ်း"},
{"st_eng":"Thamain Bayan Street","st_myn":"သမိန်ဗရမ်းလမ်း"},
{"st_eng":"Than Lwin Street","st_myn":"သံလွင်လမ်း"},
{"st_eng":"Than Thu Mar 1st Street","st_myn":"သံသုမာ ၁ လမ်း"},
{"st_eng":"Than Thu Mar 2nd Street","st_myn":"သံသုမာ ၂ လမ်း"},
{"st_eng":"Than Thu Mar 3rd Street","st_myn":"သံသုမာ ၃ လမ်း"},
{"st_eng":"Than Thu Mar Road","st_myn":"သံသုမာလမ်း"},
{"st_eng":"Thandar Street","st_myn":"သန္တလမ်း"},
{"st_eng":"Thandar Street","st_myn":"သန္တာလမ်း"},
{"st_eng":"Tharaphi Cherry Pat Lane","st_myn":"သရဖီချယ်ရီပတ်လမ်း"},
{"st_eng":"Tharaphi Street","st_myn":"သရဖီလမ်း"},
{"st_eng":"Thaw Ka Street","st_myn":"သော်ကလမ်း"},
{"st_eng":"Thayet Taw Street","st_myn":"သရက်တောလမ်း"},
{"st_eng":"Thazin Pan Street","st_myn":"သဇင်ပန်းလမ်း"},
{"st_eng":"Theik Pan Street","st_myn":"သိပ္ပံလမ်း"},
{"st_eng":"Theingi Street","st_myn":"သိင်္ဂီငီ်္လမ်း"},
{"st_eng":"Theingi Street","st_myn":"သိင်္ဂီလမ်း"},
{"st_eng":"Thida Street","st_myn":"သီတာလမ်း"},
{"st_eng":"Thida Yaesin Street","st_myn":"သီတာရေစင်လမ်း"},
{"st_eng":"Thin Gaha Street","st_myn":"သင်္ဂဟလမ်း"},
{"st_eng":"Thinda Street","st_myn":"သီတာလမ်း"},
{"st_eng":"Thingaha Street","st_myn":"သင်္ဂဟလမ်း"},
{"st_eng":"Thiri Ayer Street","st_myn":"သီရိဧရာလမ်း"},
{"st_eng":"Thiri Gayhar Street","st_myn":"သီရိဂေဟာလမ်း"},
{"st_eng":"Thiri Gon Housing Street","st_myn":"သီရိဂုဏ်အိမ်ရာလမ်း"},
{"st_eng":"Thiri Haymar Street","st_myn":"သီရိဟေမာလမ်း"},
{"st_eng":"Thiri Kaymar Street","st_myn":"သီရိခေမာလမ်း"},
{"st_eng":"Thiri Marlar Street","st_myn":"သီရိမာလာလမ်း"},
{"st_eng":"Thiri Marlar Street","st_myn":"သီရီမာလာလမ်း"},
{"st_eng":"Thiri Myaing Street","st_myn":"သီရိမြိုင်လမ်း"},
{"st_eng":"Thiri Wai Bar Street","st_myn":"သီရိဝေဘာလမ"},
{"st_eng":"Thiri Wai Bar Street","st_myn":"သီရိဝေဘာလမ်း"},
{"st_eng":"Thiri Yadanar Street","st_myn":"သီရိရတနာလမ်း"},
{"st_eng":"Thiri Zayar Street","st_myn":"သီရိဇေယျာလမ်း"},
{"st_eng":"Thit Khwa Street","st_myn":"သစ်ခွလမ်း"},
{"st_eng":"Thit Yar Pin Lane (3)","st_myn":"သစ်ယာပင်လမ်းသွယ်၃လမ်း"},
{"st_eng":"Thit Yar Pin Lane 3","st_myn":"သစ်ယာပင်လမ်းသွယ် ၃"},
{"st_eng":"Thit Yar Pin Street","st_myn":"သစ်ယာပင်လမ်း"},
{"st_eng":"Thitsar Street","st_myn":"သစ္စာလမ်း"},
{"st_eng":"Thu Dathana 1st Street","st_myn":"သုဒဿန ၁ လမ်း"},
{"st_eng":"Thu Dathana 2nd Street","st_myn":"သုဒဿန ၂ လမ်း"},
{"st_eng":"Thu Dathana 3rd Street","st_myn":"သုဒဿန ၃ လမ်း"},
{"st_eng":"Thu Dathana 4th Street","st_myn":"သုဒဿန ၄ လမ်း"},
{"st_eng":"Thu Dathana Street","st_myn":"သုဒဿနလမ်း"},
{"st_eng":"Thu Dhamar 1st Street","st_myn":"သုဓမ္မာ ၁ လမ်း"},
{"st_eng":"Thu Dhamar Road","st_myn":"ရတနာပုံလမ်း"},
{"st_eng":"Thu Dhamar Road","st_myn":"သုဓမ္မာလမ်း"},
{"st_eng":"Thu Khitar Street","st_myn":"သုခိတာလမ်း"},
{"st_eng":"Thu Mingalar 1st Street","st_myn":"သုမင်္ဂလာ ၁ လမ်း"},
{"st_eng":"Thu Mingalar 2nd Street","st_myn":"သုမင်္ဂလာ ၂ လမ်း"},
{"st_eng":"Thu Mingalar 3rd Street","st_myn":"သုမင်္ဂလာ ၃ လမ်း"},
{"st_eng":"Thu Mingalar 4th Street","st_myn":"သုမင်္ဂလာ ၄ လမ်း"},
{"st_eng":"Thu Mingalar 5th Street","st_myn":"သုမင်္ဂလာ ၅ လမ်း"},
{"st_eng":"Thu Mingalar 6th Street","st_myn":"သုမင်္ဂလာ ၆ လမ်း"},
{"st_eng":"Thu Mingalar Lane","st_myn":"သုမင်္ဂလာလမ်းသွယ်"},
{"st_eng":"Thu Mingalar Road","st_myn":"သုမင်္ဂလာလမ်း"},
{"st_eng":"Thu Mingalar Street","st_myn":"သုမင်္ဂလာလမ်း"},
{"st_eng":"Thu Nandar 10th Street","st_myn":"သုနန္ဒာ ၁၀ လမ်း"},
{"st_eng":"Thu Nandar 2nd Street","st_myn":"သုနန္ဒာ ၂ လမ်း"},
{"st_eng":"Thu Nandar 4th Street","st_myn":"သုနန္ဒာ ၄ လမ်း"},
{"st_eng":"Thu Nandar 8th Street","st_myn":"သုနန္ဒာ ၈ လမ်း"},
{"st_eng":"Thu Nandar 9th Street","st_myn":"သုနန္ဒာ ၉ လမ်း"},
{"st_eng":"Thu Nandar Street","st_myn":"သုနန္ဒာလမ်း"},
{"st_eng":"Thu Seik Ta Street","st_myn":"သုစိတ္တလမ်း"},
{"st_eng":"Thu Seik Tar Street","st_myn":"သုစိတ္တာလမ်း"},
{"st_eng":"Thukha Street","st_myn":"သုခလမ်း"},
{"st_eng":"Thumana 1st Street","st_myn":"သုမန ၁ လမ်း"},
{"st_eng":"Thumana 2nd Street","st_myn":"သုမန ၂ လမ်း"},
{"st_eng":"Thumana 3rd Street","st_myn":"သုခုမ ၃ လမ်း"},
{"st_eng":"Thumana 4th Street","st_myn":"သုမန ၄ လမ်း"},
{"st_eng":"Thumana Street","st_myn":"သုမနလမ်း"},
{"st_eng":"U Ba Han Lane","st_myn":"ဦးဘဟန်လမ်းသွယ်"},
{"st_eng":"U Ba Han Street","st_myn":"ဥိးဘဟန်လမ်း"},
{"st_eng":"U Ba Han Street","st_myn":"ဦးဘဟန်လမ်း"},
{"st_eng":"U Ba Hla Street","st_myn":"ဦးဘလှလမ်း"},
{"st_eng":"U Ba San Street","st_myn":"ဦးဘစံလမ်း"},
{"st_eng":"U Meik Street","st_myn":"ဦးမိတ်လမ်း"},
{"st_eng":"U Nay Win Street","st_myn":"ဦးနေဝင်းလမ်း"},
{"st_eng":"U Nyo Street","st_myn":"ဦးညိုလမ်း"},
{"st_eng":"U Pe Thin Street","st_myn":"ဦးဖေသင်လမ်း"},
{"st_eng":"U San Pe Street","st_myn":"ဦးစံပီလမ်း"},
{"st_eng":"U Tin Oo Street","st_myn":"ဦးတင်ဦးလမ်း"},
{"st_eng":"U Tun Tin Street","st_myn":"ဦးထွန်းတင်လမ်း"},
{"st_eng":"Wai Thanta Yar Street","st_myn":"ဝေသန္တရာလမ်း"},
{"st_eng":"Waizayandar Atwin Street","st_myn":"ဝေဇယန္တာအတွင်းလမ်း"},
{"st_eng":"Waizayandar Rd.","st_myn":"ဝေဇယန္တာလမ်း"},
{"st_eng":"Waizayandar Road","st_myn":"ဝေဇယန္တာလမ်း"},
{"st_eng":"Waizayandar Yeik Thar 1st Street","st_myn":"ဝေဇယန္တာရိပ်သာ ၁ လမ်း"},
{"st_eng":"Waizayandar Yeik Thar 1th Street","st_myn":"ဝေဇယန္တာရိပ်သာ ၁ လမ်း"},
{"st_eng":"Waizayandar Yeik Thar 2nd Street","st_myn":"ဝေဇယန္တာရိပ်သာ ၂ လမ်း"},
{"st_eng":"Waizayandar Yeik Thar 2th Street","st_myn":"ဝေဇယန္တာရိပ်သာ ၂ လမ်း"},
{"st_eng":"Waizayandar Yeik Thar 3th Street","st_myn":"ဝေဇယန္တာရိပ်သာ ၃ လမ်း"},
{"st_eng":"Waizayandar Yeik Thar 4th Street","st_myn":"ဝေဇယန္တာရိပ်သာ ၄ လမ်း"},
{"st_eng":"Waizayandar Yeik Thar 5th Street","st_myn":"ဝေဇယန္တာရိပ်သာ ၅ လမ်း"},
{"st_eng":"War So Oo Street","st_myn":"ဝါဆိုဦးလမ်း"},
{"st_eng":"Wut Yi Street","st_myn":"ဝတ်ရည်လမ်း"},
{"st_eng":"Yadanar Bon Street","st_myn":"ရတနာပုံလမ်း"},
{"st_eng":"Yadanar Bon Street","st_myn":"ဝ"},
{"st_eng":"Yadanar Depa Street","st_myn":"ရတနာဒီပလမ်း"},
{"st_eng":"Yadanar Myintzu Street","st_myn":"ရတနာမဉ္ဇူလမ်း"},
{"st_eng":"Yadanar Rd.","st_myn":"ရတနာလမ်း"},
{"st_eng":"Yadanar Road","st_myn":"ရတနာလမ်း"},
{"st_eng":"Yadanar St","st_myn":"ရတနာလမ်း"},
{"st_eng":"Yadanar Street","st_myn":"ရတနာလမ်း"},
{"st_eng":"Yadanar Theik Pan 1st Street","st_myn":"ရတနာသိပ္ပံ ၁ လမ်း"},
{"st_eng":"Yadanar Theik Pan 2nd Street","st_myn":"ရတနာသိပ္ပံ ၂ လမ်း"},
{"st_eng":"Yadanar Theik Pan Street","st_myn":"ရတနာသိပ္ပံလမ်း"},
{"st_eng":"Yadanar Theikdi Street","st_myn":"ရတနာသိဒ္ဓိလမ်း"},
{"st_eng":"Yadanar Theikpan 1st Street","st_myn":"ရတနာသိပ္ပံ ၁ လမ်း"},
{"st_eng":"Yadanar Theikpan 2nd Street","st_myn":"ရတနာသိပ္ပံ ၂ လမ်း"},
{"st_eng":"Yadanar Theikpan Street","st_myn":"ရတနာသိပ္ပံလမ်း"},
{"st_eng":"Yadanar Thiri Street","st_myn":"ရတနာသီရိလမ်း"},
{"st_eng":"Yadanar Thukha Lane","st_myn":"ရတနာသုခလမ်းသွယ်"},
{"st_eng":"Yadanar Thukha Street","st_myn":"ရတနာသုခလမ်း"},
{"st_eng":"Yae Myaung Street","st_myn":"ရေမြောင်းလမ်း"},
{"st_eng":"Yae Myaunge Sreet","st_myn":"ရေမြောင်းလမ်း"},
{"st_eng":"Yae Nan Thar Street","st_myn":"ရေနံ့သာလမ်း"},
{"st_eng":"Yae Nan Thar Street","st_myn":"ရေနံသာလမ်း"},
{"st_eng":"Yae Nant Thar Street","st_myn":"ရေနံ့သာလမ်း"},
{"st_eng":"Yae Sin Street","st_myn":"ရေစင်လမ်း"},
{"st_eng":"Yae Twin Street","st_myn":"ရေတွင်းလမ်း"},
{"st_eng":"Yan Aung Street","st_myn":"ရန်အောင်လမ်း"},
{"st_eng":"Yan Kin St","st_myn":"ရန်ကင်းလမ်း"},
{"st_eng":"Yan Kin Street","st_myn":"ရန်ကင်းလမ်း"},
{"st_eng":"Yan Nyein St","st_myn":"ရန်ငြိမ်းလမ်း"},
{"st_eng":"Yan Nyein Street","st_myn":"ရန်ငြိမ်းလမ်း"},
{"st_eng":"Yan Shin Street","st_myn":"ရန်ရျင်းလမ်း"},
{"st_eng":"Yan Shin Street","st_myn":"ရန်ရှင်းလမ်း"},
{"st_eng":"Yeik Thar 1st Street","st_myn":"ရိပ်သာ ၁ လမ်း"},
{"st_eng":"Yeik Thar 2nd Street","st_myn":"ရိပ်သာ ၂ လမ်း"},
{"st_eng":"Yeik Thar 3rd Street","st_myn":"ရိပ်သာ ၃ လမ်း"},
{"st_eng":"Yeik Thar 3th Street","st_myn":"ရိပ်သာ ၃ လမ်း"},
{"st_eng":"Yeik Thar 4rd Street","st_myn":"ရိပ်သာ ၄ လမ်း"},
{"st_eng":"Yeik Thar 4th Street","st_myn":"ရိပ်သာ ၄ လမ်း"},
{"st_eng":"Yeik Thar 5rd Street","st_myn":"ရိပ်သာ ၅ လမ်း"},
{"st_eng":"Yeik Thar 5th Steet","st_myn":"ရိပ်သာ ၅ လမ်း"},
{"st_eng":"Yeik Thar 5th Street","st_myn":"ရိပ်သာ ၅ လမ်း"},
{"st_eng":"Yeik Thar St","st_myn":"့ရိပ်သာလမ်း"},
{"st_eng":"Yeik Thar Street","st_myn":"ရိပ်သာလမ်း"},
{"st_eng":"Yin Mar Myaing Street","st_myn":"ယင်းမာမြိုင်လမ်း"},
{"st_eng":"Yin Mar Myint Street","st_myn":"ယင်းမာမြင့်လမ်း"},
{"st_eng":"Yin Mar Myint Street","st_myn":"ယင်းမာမြိုင်လမ်း"},
{"st_eng":"Yu Wa Street","st_myn":"ယုဝလမ်း"},
{"st_eng":"Yu Wa Street","st_myn":"ယုဝါလမ်း"},
{"st_eng":"Yukalit Myaing Street","st_myn":"ယူကလစ်မြိုင်လမ်း"},
{"st_eng":"Yuzana Lane","st_myn":"ယုဇနလမ်းသွယ်"},
{"st_eng":"Yuzana Street","st_myn":"ယုဇနလမ်း"},
{"st_eng":"Ywar Hlay Street","st_myn":"ရွာလယ်လမ်း"},
{"st_eng":"Ywar Lae  Street","st_myn":"ရွာလယ်လမ်း"},
{"st_eng":"Ywar Lae Lane","st_myn":"ရွာလယ်လမ်းသွယ်"},
{"st_eng":"Ywar Lae Street","st_myn":"ရွာလယ်လမ်း"},
{"st_eng":"Za Hti La 1st Street","st_myn":"ဇဋိလ ၁ လမ်း"},
{"st_eng":"Za Hti La 2nd Street","st_myn":"ဇဋိလ ၂ လမ်း"},
{"st_eng":"Za Hti La 3rd Street","st_myn":"ဇဋိလ ၃ လမ်း"},
{"st_eng":"Za Hti La 4th Street","st_myn":"ဇဋိလ ၄ လမ်း"},
{"st_eng":"Zabu Kyattayae Saung Street","st_myn":"ဇမ္ဗူကျက်သရေဆောင်လမ်း"},
{"st_eng":"Zabu Kyattayae Saung Street","st_myn":"ဇမ္ဗူကျက်သရေဆောင်လမ်း."},
{"st_eng":"Zabu Mandai Street","st_myn":"ဇမ္ဗူမဏိုင်လမ်း"},
{"st_eng":"Zabu Mandai Street","st_myn":"ဇမ္ဗူမဏ္ဍိုင်လမ်း"},
{"st_eng":"Zabu Myittar Lane 2","st_myn":"ဇမ္ဗူမေတ္တာလမ်းသွယ် ၂"},
{"st_eng":"Zabu Myittar Street","st_myn":"ဇမ္ဗူမေတ္တာလမ်း"},
{"st_eng":"Zabu Rit Street","st_myn":"ဇမ္ဗူရစ်လမ်း"},
{"st_eng":"Zabu Theingi Street","st_myn":"ဇမ္ဗူသိင်္ဂီလမ်း"},
{"st_eng":"Zabu Theingi Street","st_myn":"ဇမ္ဗူသီင်္ဂီလမ်း"},
{"st_eng":"Zabu Thiri Street","st_myn":"ဇမ္ဗူသီရိလမ်း"},
{"st_eng":"Zabudate Street","st_myn":"ဇမ္ဗူဒိပ်လမ်း"},
{"st_eng":"Zagawar 2nd Street","st_myn":"စကားဝါ ၂ လမ်း"},
{"st_eng":"Zagawar 2nd Street","st_myn":"စကားဝါလမ်း"},
{"st_eng":"Zagawar 3rd Street","st_myn":"စကားဝါ ၃ လမ်း"},
{"st_eng":"Zagawar 3rd Street","st_myn":"စကားဝါလမ်း"},
{"st_eng":"Zagawar Street","st_myn":"စကားဝါလမ်း"},
{"st_eng":"Zaw Ti Ka 1st Street","st_myn":"ဇောတိက ၁ လမ်း"},
{"st_eng":"Zaw Ti Ka Street","st_myn":"ဇောတိကလမ်း"},
{"st_eng":"Zawana Street","st_myn":"ဇဝနလမ်း"},
{"st_eng":"Zawtika Eainyar Street","st_myn":"ဇောတိကအိမ်ယာလမ်း"},
{"st_eng":"Zawtika Housing Street","st_myn":"ဇောတိကအိမ်ယာလမ်း"},
{"st_eng":"Zaya Thukha 2nd Street","st_myn":"ဇေယျာသုခ ၂ လမ်း"},
{"st_eng":"Zaya Thukha Street","st_myn":"ဇေယျသုခလမ်း"},
{"st_eng":"Zaya Thukha Street","st_myn":"ဇေယျာသုခလမ်း"},
{"st_eng":"Zayar Thiri Street","st_myn":"ဇေယျာသီရိလမ်း"},
{"st_eng":"Zayar Thukha 2nd Street","st_myn":"ဇေယျာသုခ ၂ လမ်း"},
{"st_eng":"Zayar Thukha Street","st_myn":"ဇေယျာသုခလမ်း"}
]
}